linkedinputs/__init__.py
linkedinputs/input_types.py
linkedinputs/linkedinputs.py
linkedinputs-0.0.2.dist-info/LICENSE
linkedinputs-0.0.2.dist-info/METADATA
linkedinputs-0.0.2.dist-info/WHEEL
linkedinputs-0.0.2.dist-info/top_level.txt
linkedinputs-0.0.2.dist-info/RECORD
