Metadata-Version: 2.1
Name: linkedinputs
Version: 0.0.2
Summary: linked inputs for flet framework
Home-page: https://github.com/naderidev/linkedinputs
Author: naderidev
Author-email: mohammadrezanaderi84@gmail.com
License: LICENSE
Keywords: flet,pin input,pininput,TextField,python,field,naderidev,text field
Classifier: Development Status :: 4 - Beta
Classifier: Intended Audience :: Developers
Classifier: Topic :: Software Development :: Libraries :: Python Modules
Classifier: Programming Language :: Python :: 3.10
Classifier: License :: OSI Approved :: MIT License
Requires-Python: >=3.9
License-File: LICENSE
Requires-Dist: flet
